PijushJunkFileOrg/__init__.py
PijushJunkFileOrg-0.0.0.dist-info/LICENSE.txt
PijushJunkFileOrg-0.0.0.dist-info/METADATA
PijushJunkFileOrg-0.0.0.dist-info/WHEEL
PijushJunkFileOrg-0.0.0.dist-info/top_level.txt
PijushJunkFileOrg-0.0.0.dist-info/RECORD
