Metadata-Version: 2.1
Name: PijushJunkFileOrg
Version: 0.0.0
Summary: This is File Organizer Python Module
Home-page: https://github.com/pijush-konar-au7/Python-Project
Author: Pijush
Author-email: UNKNOWN
License: UNKNOWN
Platform: UNKNOWN
